postlang/__init__.py
postlang/client.py
postlang/consumer.py
postlang/jsonutil.py
postlang/poller.py
postlang/request.py
postlang/utils.py
postlang/version.py
postlang/test/__init__.py
postlang/test/test_client.py
postlang/test/test_consumer.py
postlang/test/test_jsonutil.py
postlang/test/test_module.py
postlang/test/test_request.py
postlang/test/test_utils.py
postlang-0.9.0.dist-info/LICENSE
postlang-0.9.0.dist-info/METADATA
postlang-0.9.0.dist-info/WHEEL
postlang-0.9.0.dist-info/top_level.txt
postlang-0.9.0.dist-info/RECORD
